[
  {
    "name": "vampire_(blue_oath)",
    "canon_name": "vampire",
    "illustrator": "? akagi_kurage",
    "danbooru_banned": false
  },
  {
    "name": "yuura_(blue_oath)",
    "canon_name": "yuura",
    "illustrator": "? almic",
    "danbooru_banned": false
  },
  {
    "name": "kaga_(overflowing_azure)_(blue_oath)",
    "canon_name": "kaga (overflowing azure)",
    "illustrator": "? dulldull",
    "danbooru_banned": false
  },
  {
    "name": "hyuuga_(blue_oath)",
    "canon_name": "hyuuga",
    "illustrator": "nakama_daichi",
    "danbooru_banned": false
  },
  {
    "name": "ise_(blue_oath)",
    "canon_name": "ise",
    "illustrator": "nakama_daichi",
    "danbooru_banned": false
  },
  {
    "name": "le_malin_(blue_oath)",
    "canon_name": "le malin",
    "illustrator": "mamuru",
    "danbooru_banned": false
  },
  {
    "name": "le_terrible_(blue_oath)",
    "canon_name": "le terrible",
    "illustrator": "mamuru",
    "danbooru_banned": false
  },
  {
    "name": "asashi_(blue_oath)",
    "canon_name": "asashi",
    "illustrator": "? hiroya_juuren",
    "danbooru_banned": false
  },
  {
    "name": "howe_(blue_oath)",
    "canon_name": "howe",
    "illustrator": "modare",
    "danbooru_banned": false
  },
  {
    "name": "duke_of_york_(blue_oath)",
    "canon_name": "duke of york",
    "illustrator": "modare",
    "danbooru_banned": false
  },
  {
    "name": "astoria_(blue_oath)",
    "canon_name": "astoria",
    "illustrator": "? sg_(satoumogumogu)",
    "danbooru_banned": false
  },
  {
    "name": "graf_zeppelin_(blue_oath)",
    "canon_name": "graf zeppelin",
    "illustrator": "? cofepig",
    "danbooru_banned": false
  },
  {
    "name": "belfast_(blue_oath)",
    "canon_name": "belfast",
    "illustrator": "muryotaro",
    "danbooru_banned": true
  },
  {
    "name": "strasbourg_(blue_oath)",
    "canon_name": "strasbourg",
    "illustrator": "soukou_makura",
    "danbooru_banned": false
  },
  {
    "name": "sparviero_(blue_oath)",
    "canon_name": "sparviero",
    "illustrator": "atte_nanakusa",
    "danbooru_banned": false
  },
  {
    "name": "hood_(rutile_radiance)_(blue_oath)",
    "canon_name": "hood (rutile radiance)",
    "illustrator": "aiko_(kanl)",
    "danbooru_banned": true
  },
  {
    "name": "hiryuu_(autumn_skin)_(blue_oath)",
    "canon_name": "hiryuu (autumn skin)",
    "illustrator": "oooomiga",
    "danbooru_banned": false
  },
  {
    "name": "artigliere_(blue_oath)",
    "canon_name": "artigliere",
    "illustrator": "fangdan_runiu",
    "danbooru_banned": false
  },
  {
    "name": "maxim_gorky_(blue_oath)",
    "canon_name": "maxim gorky",
    "illustrator": "muryotaro",
    "danbooru_banned": true
  },
  {
    "name": "andrea_doria_(blue_oath)",
    "canon_name": "andrea doria",
    "illustrator": "seinen",
    "danbooru_banned": false
  },
  {
    "name": "king_george_v_(blue_oath)",
    "canon_name": "king george v",
    "illustrator": "modare",
    "danbooru_banned": false
  },
  {
    "name": "alaska_(blue_oath)",
    "canon_name": "alaska",
    "illustrator": "evan_yang",
    "danbooru_banned": true
  },
  {
    "name": "dorsetshire_(blue_oath)",
    "canon_name": "dorsetshire",
    "illustrator": "fangdan_runiu",
    "danbooru_banned": false
  },
  {
    "name": "norfolk_(blue_oath)",
    "canon_name": "norfolk",
    "illustrator": "fangdan_runiu",
    "danbooru_banned": false
  },
  {
    "name": "haguro_(blue_oath)",
    "canon_name": "haguro",
    "illustrator": "oooomiga",
    "danbooru_banned": false
  },
  {
    "name": "tuscaloosa_(blue_oath)",
    "canon_name": "tuscaloosa",
    "illustrator": "oooomiga",
    "danbooru_banned": false
  },
  {
    "name": "hornet_(blue_oath)",
    "canon_name": "hornet",
    "illustrator": "scottie_(phantom2)",
    "danbooru_banned": false
  },
  {
    "name": "yorktown_(blue_oath)",
    "canon_name": "yorktown",
    "illustrator": "scottie_(phantom2)",
    "danbooru_banned": false
  },
  {
    "name": "tirpitz_(blue_oath)",
    "canon_name": "tirpitz",
    "illustrator": "? baek_hyang",
    "danbooru_banned": false
  },
  {
    "name": "admiral_scheer_(blue_oath)",
    "canon_name": "admiral scheer",
    "illustrator": "? kome_cola",
    "danbooru_banned": false
  },
  {
    "name": "lightning_(blue_oath)",
    "canon_name": "lightning",
    "illustrator": "? kenken_(keuken)",
    "danbooru_banned": false
  },
  {
    "name": "john_c._butler_(blue_oath)",
    "canon_name": "john c. butler",
    "illustrator": "? miyamoya",
    "danbooru_banned": false
  },
  {
    "name": "prince_of_wales_(blue_oath)",
    "canon_name": "prince of wales",
    "illustrator": "modare",
    "danbooru_banned": false
  },
  {
    "name": "ping_hai_(blue_oath)",
    "canon_name": "ping hai",
    "illustrator": "criin",
    "danbooru_banned": true
  },
  {
    "name": "hood_(blue_oath)",
    "canon_name": "hood",
    "illustrator": "aiko_(kanl)",
    "danbooru_banned": true
  },
  {
    "name": "seydlitz_(blue_oath)",
    "canon_name": "seydlitz",
    "illustrator": "? kim_eb",
    "danbooru_banned": false
  },
  {
    "name": "naka_(blue_oath)",
    "canon_name": "naka",
    "illustrator": "? goyain",
    "danbooru_banned": false
  },
  {
    "name": "shoukaku_(blue_oath)",
    "canon_name": "shoukaku",
    "illustrator": "gaou_(umaiyo_puyoman)",
    "danbooru_banned": false
  },
  {
    "name": "oakland_(blue_oath)",
    "canon_name": "oakland",
    "illustrator": "jhcrow3",
    "danbooru_banned": false
  },
  {
    "name": "admiral_hipper_(blue_oath)",
    "canon_name": "admiral hipper",
    "illustrator": "? freewaterlemon",
    "danbooru_banned": false
  },
  {
    "name": "albatros_(blue_oath)",
    "canon_name": "albatros",
    "illustrator": "? yukizuki_chikuba",
    "danbooru_banned": false
  },
  {
    "name": "saumarez_(blue_oath)",
    "canon_name": "saumarez",
    "illustrator": "itamidome",
    "danbooru_banned": false
  },
  {
    "name": "savage_(blue_oath)",
    "canon_name": "savage",
    "illustrator": "itamidome",
    "danbooru_banned": false
  },
  {
    "name": "cleveland_(blue_oath)",
    "canon_name": "cleveland",
    "illustrator": "orokanahime",
    "danbooru_banned": false
  },
  {
    "name": "helena_(blue_oath)",
    "canon_name": "helena",
    "illustrator": "? whoosaku",
    "danbooru_banned": false
  },
  {
    "name": "wasp_(blue_oath)",
    "canon_name": "wasp",
    "illustrator": "? whoosaku",
    "danbooru_banned": false
  },
  {
    "name": "queen_elizabeth_(blue_oath)",
    "canon_name": "queen elizabeth",
    "illustrator": "? whoosaku",
    "danbooru_banned": false
  },
  {
    "name": "nimitz_(blue_oath)",
    "canon_name": "nimitz",
    "illustrator": "? hanato_(seonoaiko)",
    "danbooru_banned": false
  },
  {
    "name": "molotov_(blue_oath)",
    "canon_name": "molotov",
    "illustrator": "muryotaro",
    "danbooru_banned": true
  },
  {
    "name": "jervis_(blue_oath)",
    "canon_name": "jervis",
    "illustrator": "itamidome",
    "danbooru_banned": false
  },
  {
    "name": "prinz_eugen_(blue_oath)",
    "canon_name": "prinz eugen",
    "illustrator": "? kanzaki_kureha",
    "danbooru_banned": false
  },
  {
    "name": "yuudachi_(blue_oath)",
    "canon_name": "yuudachi",
    "illustrator": "waterkuma",
    "danbooru_banned": false
  },
  {
    "name": "takao_(blue_oath)",
    "canon_name": "takao",
    "illustrator": "? nicchi",
    "danbooru_banned": false
  },
  {
    "name": "atago_(blue_oath)",
    "canon_name": "atago",
    "illustrator": "? yukizuki_chikuba",
    "danbooru_banned": false
  },
  {
    "name": "samuel_b._roberts_(blue_oath)",
    "canon_name": "samuel b. roberts",
    "illustrator": "? buta_tamako",
    "danbooru_banned": false
  },
  {
    "name": "souryuu_(blue_oath)",
    "canon_name": "souryuu",
    "illustrator": "oooomiga",
    "danbooru_banned": false
  },
  {
    "name": "kaga_(blue_oath)",
    "canon_name": "kaga",
    "illustrator": "? shi_(yuzuki)",
    "danbooru_banned": false
  },
  {
    "name": "volta_(blue_oath)",
    "canon_name": "volta",
    "illustrator": "xiao_chichi",
    "danbooru_banned": false
  },
  {
    "name": "zuikaku_(blue_oath)",
    "canon_name": "zuikaku",
    "illustrator": "gaou_(umaiyo_puyoman)",
    "danbooru_banned": false
  },
  {
    "name": "le_fantasque_(blue_oath)",
    "canon_name": "le fantasque",
    "illustrator": "mamuru",
    "danbooru_banned": false
  },
  {
    "name": "san_francisco_(blue_oath)",
    "canon_name": "san francisco",
    "illustrator": "rainli",
    "danbooru_banned": false
  },
  {
    "name": "unknown_h_(blue_oath)",
    "canon_name": "unknown h",
    "illustrator": "? whoosaku",
    "danbooru_banned": false
  },
  {
    "name": "scharnhorst_(blue_oath)",
    "canon_name": "scharnhorst",
    "illustrator": "? cofepig",
    "danbooru_banned": false
  }
]